src/__init__.py
src/api/__init__.py
src/api/app.py
src/api/calculator.py
src/cli/__init__.py
src/cli/calculator.py
src/cli/greeter.py
src/core/__init__.py
src/core/calculator.py
src/core/greeter.py
binnev_python_template-5.3.0.dist-info/METADATA
binnev_python_template-5.3.0.dist-info/WHEEL
binnev_python_template-5.3.0.dist-info/entry_points.txt
binnev_python_template-5.3.0.dist-info/top_level.txt
binnev_python_template-5.3.0.dist-info/RECORD
